spotipy2/__init__.py
spotipy2/client.py
spotipy2/exceptions.py
spotipy2/auth/__init__.py
spotipy2/auth/base_auth_flow.py
spotipy2/auth/client_credentials_flow.py
spotipy2/auth/oauth_flow.py
spotipy2/auth/token.py
spotipy2/methods/__init__.py
spotipy2/methods/albums.py
spotipy2/methods/artists.py
spotipy2/methods/playlists.py
spotipy2/methods/search.py
spotipy2/methods/tracks.py
spotipy2/types/__init__.py
spotipy2/types/album.py
spotipy2/types/artist.py
spotipy2/types/base.py
spotipy2/types/paging.py
spotipy2/types/playlist.py
spotipy2/types/playlist_item.py
spotipy2/types/track.py
spotipy2/types/user.py
spotipy2-0.6.1.dist-info/LICENSE
spotipy2-0.6.1.dist-info/METADATA
spotipy2-0.6.1.dist-info/NOTICE
spotipy2-0.6.1.dist-info/WHEEL
spotipy2-0.6.1.dist-info/top_level.txt
spotipy2-0.6.1.dist-info/RECORD
