Metadata-Version: 2.1
Name: spotipy2
Version: 0.6.1
Summary: The next generation Spotify Web API wrapper for Python
Home-page: https://spotipy2.org/
Author: CyanBook
License: LGPLv3+
Download-URL: https://github.com/CyanBook/spotipy2/releases/latest
Project-URL: Tracker, https://github.com/CyanBook/spotipy2/issues
Project-URL: Community, https://github.com/CyanBook/spotipy2/discussions
Project-URL: Source, https://github.com/CyanBook/spotipy2
Keywords: spotify spotipy spotipy2 api wrapper client library oauth
Platform: UNKNOWN
Classifier: Development Status :: 4 - Beta
Classifier: Intended Audience :: Developers
Classifier: Natural Language :: English
Classifier: License :: OSI Approved :: GNU Lesser General Public License v3 or later (LGPLv3+)
Classifier: Operating System :: OS Independent
Classifier: Programming Language :: Python
Classifier: Programming Language :: Python :: 3
Classifier: Programming Language :: Python :: 3.7
Classifier: Programming Language :: Python :: 3.8
Classifier: Programming Language :: Python :: 3.9
Classifier: Programming Language :: Python :: 3.9
Classifier: Programming Language :: Python :: 3.10
Classifier: Programming Language :: Python :: Implementation
Classifier: Programming Language :: Python :: Implementation :: CPython
Classifier: Topic :: Internet
Classifier: Topic :: Software Development :: Libraries
Classifier: Topic :: Software Development :: Libraries :: Python Modules
Requires-Python: ~=3.7
Requires-Dist: aiohttp
Provides-Extra: cache
Requires-Dist: pymongo ; extra == 'cache'
